{
  "aluno-1": {
    "nome": "Gabriella Cukier",
    "email-insper": "gabriellaec@al.insper.edu.br",
    "user-github": "gabriellaec"
  },
  "aluno-2": {
    "nome": "Fernando Fincatti",
    "email-insper": "fernandocfbf@al.insper.edu.br",
    "user-github": "fernandocfbf"
  },
  "aluno-3": {
    "nome": "Gabriela Mitu",
    "email-insper": "gabrielaym@al.insper.edu.br",
    "user-github": "GabrielaMitu"
  },
  "aluno-4": {
    "nome": "Ellen Shen",
    "email-insper": "ellenbs@al.insper.edu.br",
    "user-github": "ellenbs"
  },
  "aluno-5": {
    "nome": "Alexandre Markiewicz Fernandes",
    "email-insper": "alexandremf6@al.insper.edu.br",
    "user-github": "Leleco1599"
  },
  "aluno-6": {
    "nome": "Gabriela Moreno Boriero",
    "email-insper": "gabrielamb2@al.insper.edu.br",
    "user-github": "Gabrielamb2"
  }
}
